cesard/__init__.py
cesard/ancillary.py
cesard/ard.py
cesard/config.py
cesard/dem.py
cesard/search.py
cesard/snap.py
cesard/tile_extraction.py
cesard/metadata/__init__.py
cesard/metadata/extract.py
cesard/metadata/mapping.py
cesard/metadata/stac.py
cesard/metadata/xml.py
cesard-1.1.1.dist-info/licenses/LICENSE.txt
cesard-1.1.1.dist-info/METADATA
cesard-1.1.1.dist-info/WHEEL
cesard-1.1.1.dist-info/top_level.txt
cesard-1.1.1.dist-info/RECORD
