Metadata-Version: 2.4
Name: cesard
Version: 1.1.1
Summary: Central functionalities for creating Synthetic Aperture Radar (SAR) Analysis Ready Data (ARD) products
Maintainer-email: John Truckenbrodt <john.truckenbrodt@dlr.de>
License: # Copyright (c) 2021-2025, John Truckenbrodt and Marco Wolsza.
Project-URL: repository, https://github.com/SAR-ARD/cesard
Project-URL: documentation, https://cesard.readthedocs.io/en/latest/
Classifier: License :: OSI Approved :: MIT License
Classifier: Operating System :: Microsoft :: Windows
Classifier: Operating System :: POSIX :: Linux
Classifier: Programming Language :: Python :: 3
Requires-Python: >=3.10
License-File: LICENSE.txt
Requires-Dist: asf_search
Requires-Dist: gdal>=3.5.0
Requires-Dist: geopandas
Requires-Dist: lxml
Requires-Dist: multiformats>=0.3.1
Requires-Dist: numpy<2.0
Requires-Dist: pandas
Requires-Dist: pyproj
Requires-Dist: pyroSAR>=0.31.0
Requires-Dist: pystac<1.11.0,>=1.8.0
Requires-Dist: python-dateutil
Requires-Dist: requests
Requires-Dist: scipy
Requires-Dist: spatialist>=0.16.0
Provides-Extra: test
Requires-Dist: pytest; extra == "test"
Requires-Dist: requests; extra == "test"
Provides-Extra: docs
Requires-Dist: sphinx; extra == "docs"
Requires-Dist: sphinxcontrib-bibtex; extra == "docs"
Requires-Dist: nbsphinx; extra == "docs"
Requires-Dist: sphinx_rtd_theme; extra == "docs"
Requires-Dist: sphinx-toolbox; extra == "docs"
Requires-Dist: ipython; extra == "docs"
Dynamic: license-file
